st_selectable_textarea/__init__.py
st_selectable_textarea/frontend/build/asset-manifest.json
st_selectable_textarea/frontend/build/bootstrap.min.css
st_selectable_textarea/frontend/build/index.html
st_selectable_textarea/frontend/build/static/js/main.008b350c.js
st_selectable_textarea/frontend/build/static/js/main.008b350c.js.LICENSE.txt
st_selectable_textarea/frontend/build/static/js/main.008b350c.js.map
st_selectable_textarea/frontend/build/static/js/main.d2dd3902.js
st_selectable_textarea/frontend/build/static/js/main.d2dd3902.js.LICENSE.txt
st_selectable_textarea/frontend/build/static/js/main.d2dd3902.js.map
streamlit_selectable_textarea-0.1.6.dist-info/LICENSE
streamlit_selectable_textarea-0.1.6.dist-info/METADATA
streamlit_selectable_textarea-0.1.6.dist-info/WHEEL
streamlit_selectable_textarea-0.1.6.dist-info/top_level.txt
streamlit_selectable_textarea-0.1.6.dist-info/RECORD
